{"cameraMode":{"drawMode":0,"name":"Shaded","section":"Shading Mode"},"sceneLighting":true,"audioPlay":false,"sceneViewState":{"showFog":true,"showMaterialUpdate":false,"showSkybox":true,"showFlares":true,"showImageEffects":true,"showParticleSystems":true},"in2DMode":false,"pivot":{"x":553.2381591796875,"y":-60.722225189208987,"z":581.463623046875},"rotation":{"x":0.09454657882452011,"y":0.40482911467552187,"z":-0.04245338961482048,"w":0.9086670875549316},"size":330.81768798828127,"orthographic":false}